{
  "doc_key": "mitigation_plan",
  "doc_title": "Mitigation Plan",
  "doc_kind": "workflow_case",
  "status": "draft",
  "module_id": "risk_policy_management",
  "submodule_id": "risk_register",
  "app_id": "governance_compliance",
  "base_action_profile": "base_record_actions",
  "doc_archetype": "workflow_case",
  "classification": {
    "archetype": "workflow_case",
    "bundle": "administration",
    "doc_kind": "workflow_case"
  },
  "planning_source": {
    "type": "reference_doc_generation_manifest",
    "bundle": "administration",
    "app": "governance_compliance",
    "module": "risk_policy_management",
    "submodule": "risk_register",
    "reference_doc_id": "mitigation_plan",
    "evidence_gaps": [
      "action-line detail",
      "overdue rules"
    ]
  },
  "ui": {
    "icon_key": "checklist",
    "accent": "#2d6a4f",
    "logo_image": null,
    "cover_image": null,
    "preferred_views": [
      "list",
      "table",
      "detail",
      "report"
    ],
    "default_density": "comfortable"
  },
  "dashboard": {
    "version": 1,
    "surface": "doc",
    "hero": {
      "variant": "summary_strip",
      "show_breadcrumb": true,
      "show_title": true
    },
    "navigation": {
      "primary_children": "records",
      "flatten_submodules_in_ui": false,
      "views": [
        "list",
        "table",
        "detail",
        "report"
      ]
    },
    "blocks": [
      {
        "id": "kpis",
        "type": "kpi_cards",
        "title": "Mitigation Plan KPIs",
        "data_source": {
          "kind": "db",
          "entity_scope": "doc",
          "entity_id": "mitigation_plan",
          "metric_family": "overview"
        }
      },
      {
        "id": "summaries",
        "type": "summary_cards",
        "title": "Mitigation Plan summaries",
        "data_source": {
          "kind": "db",
          "entity_scope": "doc",
          "entity_id": "mitigation_plan",
          "metric_family": "summary"
        }
      },
      {
        "id": "charts",
        "type": "chart_group",
        "title": "Mitigation Plan charts",
        "data_source": {
          "kind": "db",
          "entity_scope": "doc",
          "entity_id": "mitigation_plan",
          "metric_family": "trend"
        }
      },
      {
        "id": "reports",
        "type": "report_links",
        "title": "Mitigation Plan reports",
        "data_source": {
          "kind": "db",
          "entity_scope": "doc",
          "entity_id": "mitigation_plan",
          "metric_family": "reporting"
        }
      },
      {
        "id": "records",
        "type": "record_table",
        "title": "Mitigation Plan records",
        "data_source": {
          "kind": "db",
          "entity_scope": "doc",
          "entity_id": "mitigation_plan",
          "metric_family": "records"
        }
      }
    ]
  },
  "reporting": {
    "supports_kpis": true,
    "supports_summaries": true,
    "supports_charts": true,
    "supports_reports": true,
    "default_time_grain": "month",
    "default_comparison": "previous_period",
    "default_currency_mode": "base_currency",
    "metric_sources": [
      {
        "id": "overview",
        "kind": "db",
        "entity_scope": "doc",
        "entity_id": "mitigation_plan",
        "metric_family": "overview"
      },
      {
        "id": "summary",
        "kind": "db",
        "entity_scope": "doc",
        "entity_id": "mitigation_plan",
        "metric_family": "summary"
      },
      {
        "id": "trend",
        "kind": "db",
        "entity_scope": "doc",
        "entity_id": "mitigation_plan",
        "metric_family": "trend"
      },
      {
        "id": "reporting",
        "kind": "db",
        "entity_scope": "doc",
        "entity_id": "mitigation_plan",
        "metric_family": "reporting"
      }
    ],
    "report_registry": [
      {
        "id": "overview_report",
        "label": "Mitigation Plan Overview",
        "report_type": "dashboard_summary",
        "surface": "doc"
      },
      {
        "id": "trend_report",
        "label": "Mitigation Plan Trends",
        "report_type": "trend_analysis",
        "surface": "doc"
      },
      {
        "id": "summary_report",
        "label": "Mitigation Plan Summary",
        "report_type": "summary_report",
        "surface": "doc"
      },
      {
        "id": "detail_report",
        "label": "Mitigation Plan Detail",
        "report_type": "detail_report",
        "surface": "doc"
      }
    ],
    "supports_outputs": true,
    "supports_print_formats": true,
    "default_views": [
      "summary",
      "trend",
      "report_table"
    ],
    "chart_library": {
      "renderer": "recharts",
      "recommended_package": "recharts",
      "source": "https://recharts.org/en-US"
    },
    "chart_registry": [
      {
        "id": "mitigation_plan_trend_line",
        "label": "Mitigation Plan trend",
        "chart_type": "line",
        "series_role": "time_series",
        "metric_family": "trend",
        "x_field": "period",
        "y_field": "value"
      },
      {
        "id": "mitigation_plan_volume_column",
        "label": "Mitigation Plan volume",
        "chart_type": "column",
        "series_role": "comparison",
        "metric_family": "summary",
        "x_field": "category",
        "y_field": "count"
      },
      {
        "id": "mitigation_plan_distribution_donut",
        "label": "Mitigation Plan distribution",
        "chart_type": "donut",
        "series_role": "distribution",
        "metric_family": "summary",
        "segment_field": "category",
        "value_field": "value"
      }
    ]
  },
  "flow": {
    "related_docs": [
      "risk_register_entry"
    ],
    "upstream_docs": [
      "risk_register_entry"
    ],
    "downstream_docs": [],
    "borrowed_fields": [
      "severity",
      "owner context from risk_register_entry"
    ],
    "emits_records": [],
    "downstream_effects": [],
    "actors": [
      "compliance officer"
    ],
    "handoff_targets": [
      "risk_register_entry"
    ],
    "graph_edges": [
      {
        "source_doc": "mitigation_plan",
        "target_doc": "risk_register_entry",
        "relation": "references"
      }
    ]
  },
  "contract_version": 1
}
